ksec/__init__.py
ksec/main.py
ksec-0.5.1.dist-info/METADATA
ksec-0.5.1.dist-info/WHEEL
ksec-0.5.1.dist-info/entry_points.txt
ksec-0.5.1.dist-info/licenses/LICENSE.md
ksec-0.5.1.dist-info/RECORD
