Metadata-Version: 2.3
Name: ksec
Version: 0.5.1
Summary: Kubernetes secrets pretty printer
Author-email: Tucker Beck <tucker.beck@gmail.com>
License-Expression: MIT
License-File: LICENSE.md
Requires-Python: >=3.12
Requires-Dist: auto-name-enum>=2.0.0
Requires-Dist: thefuzz>=0.22.1
Requires-Dist: typer>=0.12.5
Provides-Extra: yaml
Requires-Dist: pyyaml>=6.0.2; extra == 'yaml'
